clik_wtforms
